rosdepc/__init__.py
rosdepc/rosdepc.py
rosdepc-1.1.0.dist-info/LICENSE
rosdepc-1.1.0.dist-info/METADATA
rosdepc-1.1.0.dist-info/WHEEL
rosdepc-1.1.0.dist-info/entry_points.txt
rosdepc-1.1.0.dist-info/top_level.txt
rosdepc-1.1.0.dist-info/RECORD
