Metadata-Version: 2.1
Name: rosdepc
Version: 1.1.0
Summary: rosdep package manager abstraction tool for ROS
Home-page: https://fishros.com
Author: 小鱼
Author-email: fishros@foxmail.com
License: BSD
Keywords: ROS
Platform: UNKNOWN
Classifier: Programming Language :: Python
Classifier: License :: OSI Approved :: BSD License
License-File: LICENSE
Requires-Dist: rosdep
